secureadmin
