Metadata-Version: 1.1
Name: django-secureadmin
Version: 1.3
Summary: Django-SecureAdmin send verification mail when user last and new ip not equals.
Home-page: https://github.com/irandjango/django-secureadmin/
Author: Mahdi Fakhrabadi
Author-email: mahdi.blackhat@gmail.com
License: MIT
Keywords: secure django,django,secure django admin,django admin,secureadmin
Platform: UNKNOWN
Classifier: Environment :: Web Environment
Classifier: Framework :: Django
Classifier: Intended Audience :: Developers
Classifier: Intended Audience :: System Administrators
Classifier: License :: OSI Approved :: MIT License
Classifier: Operating System :: OS Independent
Classifier: Programming Language :: Python
Classifier: Programming Language :: Python :: 2.7
Classifier: Topic :: Internet :: WWW/HTTP :: WSGI :: Middleware
Classifier: Topic :: Security
